README.md
setup.py
easy_toolkit/__init__.py
easy_toolkit/default_settings.py
easy_toolkit/entry.py
easy_toolkit/manager.py
easy_toolkit/utils.py
easy_toolkit.egg-info/PKG-INFO
easy_toolkit.egg-info/SOURCES.txt
easy_toolkit.egg-info/dependency_links.txt
easy_toolkit.egg-info/entry_points.txt
easy_toolkit.egg-info/requires.txt
easy_toolkit.egg-info/top_level.txt
easy_toolkit/test/__init__.py
easy_toolkit/test/test_setting.py
easy_toolkit/toolkit/__init__.py
easy_toolkit/toolkit/download_all_pic.py
easy_toolkit/toolkit/website_screenshot.py
easy_toolkit/toolkit/github_commands/__init__.py
easy_toolkit/toolkit/github_commands/upload.py