Metadata-Version: 1.0
Name: easy-toolkit
Version: 0.1.5.6
Summary: UNKNOWN
Home-page: https://gitee.com/fadeaway_dai/convenient_toolkit
Author: 呆瓜
Author-email: 1032939141@qq.com
License: UNKNOWN
Platform: UNKNOWN
